nonebot_plugin_naturel_gpt_plus/__init__.py
nonebot_plugin_naturel_gpt_plus/chat.py
nonebot_plugin_naturel_gpt_plus/chat_manager.py
nonebot_plugin_naturel_gpt_plus/command_func.py
nonebot_plugin_naturel_gpt_plus/config.py
nonebot_plugin_naturel_gpt_plus/Extension.py
nonebot_plugin_naturel_gpt_plus/logger.py
nonebot_plugin_naturel_gpt_plus/matcher.py
nonebot_plugin_naturel_gpt_plus/matcher_MCRcon.py
nonebot_plugin_naturel_gpt_plus/MCrcon/COPING.txt
nonebot_plugin_naturel_gpt_plus/MCrcon/mcrcon.py
nonebot_plugin_naturel_gpt_plus/openai_func.py
nonebot_plugin_naturel_gpt_plus/persistent_data_manager.py
nonebot_plugin_naturel_gpt_plus/preset_hub_funcs.py
nonebot_plugin_naturel_gpt_plus/res/additional.css
nonebot_plugin_naturel_gpt_plus/res/additional.html
nonebot_plugin_naturel_gpt_plus/singleton.py
nonebot_plugin_naturel_gpt_plus/store.py
nonebot_plugin_naturel_gpt_plus/text_func.py
nonebot_plugin_naturel_gpt_plus/text_to_image.py
nonebot_plugin_naturel_gpt_plus/utils.py
nonebot_plugin_naturel_gpt_plus-2.2.7.dist-info/LICENSE
nonebot_plugin_naturel_gpt_plus-2.2.7.dist-info/METADATA
nonebot_plugin_naturel_gpt_plus-2.2.7.dist-info/WHEEL
nonebot_plugin_naturel_gpt_plus-2.2.7.dist-info/RECORD
