Metadata-Version: 2.1
Name: nonebot-plugin-naturel-gpt-plus
Version: 2.2.7
Summary: 一个基于NoneBot框架的Ai聊天插件，对接OpenAi文本生成接口
License: Apache-2.0
Author: KroMiose
Author-email: li_xiangff@163.com
Requires-Python: >=3.8,<4.0
Classifier: License :: OSI Approved :: Apache Software License
Classifier: Programming Language :: Python :: 3
Classifier: Programming Language :: Python :: 3.8
Classifier: Programming Language :: Python :: 3.9
Classifier: Programming Language :: Python :: 3.10
Classifier: Programming Language :: Python :: 3.11
Classifier: Programming Language :: Python :: 3.12
Requires-Dist: aiohttp (>=3.8.4,<4.0.0)
Requires-Dist: aiosmtplib (>=2.0.1,<3.0.0)
Requires-Dist: anyio (>=3.6.2,<4.0.0)
Requires-Dist: httpx (>=0.24.1,<0.25.0)
Requires-Dist: jieba (>=0.42.1,<0.43.0)
Requires-Dist: nonebot-adapter-onebot (>=2.2.1,<3.0.0)
Requires-Dist: nonebot2 (>=2.0.0rc3,<3.0.0)
Requires-Dist: numpy (>=1.21.3,<2.0.0)
Requires-Dist: openai (>=0.27.0,<=0.28.0)
Requires-Dist: pydantic (==1.10)
Requires-Dist: pyyaml (>=6.0.1,<7.0.0)
Requires-Dist: tiktoken (==0.4.0)
